DNN_printer/DNN_Printer.py
DNN_printer/DNN_printer.py
DNN_printer/__init__.py
DNN_printer-0.0.2.dist-info/DESCRIPTION.rst
DNN_printer-0.0.2.dist-info/METADATA
DNN_printer-0.0.2.dist-info/RECORD
DNN_printer-0.0.2.dist-info/WHEEL
DNN_printer-0.0.2.dist-info/entry_points.txt
DNN_printer-0.0.2.dist-info/metadata.json
DNN_printer-0.0.2.dist-info/top_level.txt
printer/__init__.py
printer/printer.py
split_layer/__init__.py
split_layer/split_layer.py
split_layer/split_layer/__init__.py
split_layer/split_layer/split_layer.py
