Metadata-Version: 2.0
Name: DNN-printer
Version: 0.0.2
Summary: Print feature map and weight size of PyTorch models.
Home-page: UNKNOWN
Author: CPing
Author-email: 635897373@qq.com
License: UNKNOWN
Platform: UNKNOWN
